marca/__init__.py
marca/data_structures/__init__.py
marca/data_structures/_car.py
marca/data_structures/_cars.py
marca/extract/__init__.py
marca/extract/_apriori.py
marca/extract/_apriori_c.py
marca/extract/_apriori_t.py
marca/extract/_base.py
marca/extract/_msapriori.py
marca/extract/_msapriori_partitioned.py
marca/predictor/__init__.py
marca/prune/__init__.py
marca/rank/__init__.py
marca/utils/__init__.py
marca/utils/dataset_transformation.py
marca/visualization/__init__.py
marca-0.1.0.dist-info/LICENSE
marca-0.1.0.dist-info/METADATA
marca-0.1.0.dist-info/WHEEL
marca-0.1.0.dist-info/RECORD
