Metadata-Version: 2.1
Name: marca
Version: 0.1.0
Summary: Modular Association Rules for Classification Algorithms
Author: Maicondalllg
Author-email: maicon.dallagnol@unesp.br
Requires-Python: >=3.8,<4.0
Classifier: Programming Language :: Python :: 3
Classifier: Programming Language :: Python :: 3.8
Classifier: Programming Language :: Python :: 3.9
Classifier: Programming Language :: Python :: 3.10
Classifier: Programming Language :: Python :: 3.11
Classifier: Programming Language :: Python :: 3.12
Requires-Dist: numpy (>=1.21.0,<2.0.0)
Requires-Dist: pandas (>=2.2.0,<3.0.0)
